{
  "name": "roq/binance_futures/json/StrategyUpdateData",
  "type": "dictionary",
  "values": [
    {
      "raw": "si",
      "name": "id",
      "type": "std/int64"
    },
    {
      "raw": "st",
      "name": "type",
      "type": "std/string_view"
    },
    {
      "raw": "ss",
      "name": "status",
      "type": "std/string_view"
    },
    {
      "raw": "s",
      "name": "symbol",
      "type": "std/string_view"
    },
    {
      "raw": "ut",
      "name": "update_time",
      "type": "std/milliseconds"
    },
    {
      "raw": "c",
      "name": "opcode",
      "type": "std/int32"
    }
  ]
}
